{"rec_date":"2017-05-04 19:46:12","data":[{"rec_date":"2017-04-16","zp":287.62,"wp":286.48,"cate":"投资类","cash":1323384,"saleNum":150,"storage_cash":5405,"storage":118},{"rec_date":"2017-04-16","zp":287.62,"wp":286.48,"cate":"工艺类","cash":439662,"saleNum":814,"storage_cash":47149,"storage":851},{"rec_date":"2017-04-17","zp":286.04,"wp":286.03,"cate":"投资类","cash":1323384,"saleNum":150,"storage_cash":5405,"storage":118},{"rec_date":"2017-04-17","zp":286.04,"wp":286.03,"cate":"工艺类","cash":441582,"saleNum":816,"storage_cash":47123,"storage":849},{"rec_date":"2017-04-18","zp":286.11,"wp":285.75,"cate":"投资类","cash":1327047,"saleNum":150,"storage_cash":5405,"storage":118},{"rec_date":"2017-04-18","zp":286.11,"wp":285.75,"cate":"工艺类","cash":448601,"saleNum":822,"storage_cash":47078,"storage":843},{"rec_date":"2017-04-20","zp":285.1,"wp":285.11,"cate":"投资类","cash":1339050,"saleNum":184,"storage_cash":4366,"storage":84},{"rec_date":"2017-04-20","zp":285.1,"wp":285.11,"cate":"工艺类","cash":462678,"saleNum":837,"storage_cash":46835,"storage":838},{"rec_date":"2017-04-21","zp":null,"wp":null,"cate":"投资类","cash":1339050,"saleNum":184,"storage_cash":4366,"storage":84},{"rec_date":"2017-04-21","zp":null,"wp":null,"cate":"工艺类","cash":462678,"saleNum":837,"storage_cash":46835,"storage":838},{"rec_date":"2017-04-22","zp":null,"wp":null,"cate":"投资类","cash":1338530,"saleNum":184,"storage_cash":4366,"storage":84},{"rec_date":"2017-04-22","zp":null,"wp":null,"cate":"工艺类","cash":464119,"saleNum":841,"storage_cash":46667,"storage":834},{"rec_date":"2017-04-23","zp":284.46,"wp":283.49,"cate":"投资类","cash":1338530,"saleNum":184,"storage_cash":4366,"storage":84},{"rec_date":"2017-04-23","zp":284.46,"wp":283.49,"cate":"工艺类","cash":465557,"saleNum":845,"storage_cash":46497,"storage":830},{"rec_date":"2017-04-24","zp":283.54,"wp":283.39,"cate":"投资类","cash":1331488,"saleNum":185,"storage_cash":4301,"storage":83},{"rec_date":"2017-04-24","zp":283.54,"wp":283.39,"cate":"工艺类","cash":466753,"saleNum":847,"storage_cash":46103,"storage":828},{"rec_date":"2017-04-25","zp":282.31,"wp":282.17,"cate":"投资类","cash":1331752,"saleNum":185,"storage_cash":4301,"storage":83},{"rec_date":"2017-04-25","zp":282.31,"wp":282.17,"cate":"工艺类","cash":466753,"saleNum":847,"storage_cash":46103,"storage":828},{"rec_date":"2017-04-26","zp":282.77,"wp":282.81,"cate":"投资类","cash":1331752,"saleNum":185,"storage_cash":4301,"storage":83},{"rec_date":"2017-04-26","zp":282.77,"wp":282.81,"cate":"工艺类","cash":466753,"saleNum":847,"storage_cash":46103,"storage":828},{"rec_date":"2017-04-27","zp":282.69,"wp":282.67,"cate":"投资类","cash":1330666,"saleNum":195,"storage_cash":3541,"storage":73},{"rec_date":"2017-04-27","zp":282.69,"wp":282.67,"cate":"工艺类","cash":473443,"saleNum":854,"storage_cash":46080,"storage":821},{"rec_date":"2017-04-28","zp":null,"wp":null,"cate":"投资类","cash":1330219,"saleNum":195,"storage_cash":3541,"storage":73},{"rec_date":"2017-04-28","zp":null,"wp":null,"cate":"工艺类","cash":474869,"saleNum":858,"storage_cash":46217,"storage":839},{"rec_date":"2017-04-30","zp":null,"wp":null,"cate":"投资类","cash":1330219,"saleNum":195,"storage_cash":3541,"storage":73},{"rec_date":"2017-04-30","zp":null,"wp":null,"cate":"工艺类","cash":477480,"saleNum":866,"storage_cash":46206,"storage":841},{"rec_date":"2017-05-02","zp":null,"wp":null,"cate":"投资类","cash":1330219,"saleNum":195,"storage_cash":3541,"storage":73},{"rec_date":"2017-05-02","zp":null,"wp":null,"cate":"工艺类","cash":477480,"saleNum":866,"storage_cash":46206,"storage":841},{"rec_date":"2017-05-03","zp":null,"wp":null,"cate":"投资类","cash":1318487,"saleNum":195,"storage_cash":3541,"storage":73},{"rec_date":"2017-05-03","zp":null,"wp":null,"cate":"工艺类","cash":479939,"saleNum":871,"storage_cash":46164,"storage":836}]}