{"shop_id":"71230401","user_id":"859752587","shop_title":"福泽人珠宝旗舰店","total_page":"5","shop_Url":"//fookchakyan.tmall.com","items":[{"item_id":544115323266,"title":"FOOK CHAK YAN/福泽人黄金戒指 足金999镂空指环女款免工费计价","img":"//img.alicdn.com/bao/uploaded/i1/TB1RSA6PVXXXXafXFXXXXXXXXXX_!!0-item_pic.jpg","sold":"0","quantity":0,"totalSoldQuantity":0,"url":"//detail.m.tmall.com/item.htm?id=544115323266","price":"1171.20"},{"item_id":548137775489,"title":"FOOK CHAK YAN/福泽人足金吊坠 黄金鸡宝宝坠子送礼佳品 计价","img":"//img.alicdn.com/bao/uploaded/i4/TB18j_vQpXXXXXvapXXXXXXXXXX_!!0-item_pic.jpg","sold":"0","quantity":0,"totalSoldQuantity":0,"url":"//detail.m.tmall.com/item.htm?id=548137775489","price":"915.20"},{"item_id":548050666922,"title":"FOOK CHAK YAN/福泽人白18K金钻石女戒 经典求婚戒指可定制 定价","img":"//img.alicdn.com/bao/uploaded/i4/TB1Znj3QpXXXXcNXXXXXXXXXXXX_!!0-item_pic.jpg","sold":"0","quantity":0,"totalSoldQuantity":0,"url":"//detail.m.tmall.com/item.htm?id=548050666922","price":"35750.00"},{"item_id":548812740155,"title":"FOOK CHAK YAN/福泽人足金手镯 杜鹃花活口可调节黄金手镯计价","img":"//img.alicdn.com/bao/uploaded/i4/TB10VO5QFXXXXa9XVXXXXXXXXXX_!!0-item_pic.jpg","sold":"0","quantity":0,"totalSoldQuantity":0,"url":"//detail.m.tmall.com/item.htm?id=548812740155","price":"8108.80"},{"item_id":548058348449,"title":"FOOK CHAK YAN/福泽人足金吊坠 音符花黄金坠子柔和精美款 计价","img":"//img.alicdn.com/bao/uploaded/i2/TB1iEAoQpXXXXbbXXXXXXXXXXXX_!!0-item_pic.jpg","sold":"0","quantity":0,"totalSoldQuantity":0,"url":"//detail.m.tmall.com/item.htm?id=548058348449","price":"816.00"},{"item_id":548813080495,"title":"FOOK CHAK YAN/福泽人足金手镯 步履MF足金999细圈手镯手饰19计价","img":"//img.alicdn.com/bao/uploaded/i2/TB1W.mBQFXXXXXQaFXXXXXXXXXX_!!0-item_pic.jpg","sold":"0","quantity":0,"totalSoldQuantity":0,"url":"//detail.m.tmall.com/item.htm?id=548813080495","price":"3955.20"},{"item_id":548057148978,"title":"FOOK CHAK YAN/福泽人足金吊坠 黄金葡萄坠子精致款 计价","img":"//img.alicdn.com/bao/uploaded/i1/TB1Kgr7QpXXXXb_XFXXXXXXXXXX_!!0-item_pic.jpg","sold":"0","quantity":0,"totalSoldQuantity":0,"url":"//detail.m.tmall.com/item.htm?id=548057148978","price":"595.20"},{"item_id":543750536702,"title":"FOOK CHAK YAN/福泽人足金情侣对戒 黄金心电图心跳硬金戒指定价","img":"//img.alicdn.com/bao/uploaded/i1/TB1rdsyPVXXXXaRapXXXXXXXXXX_!!0-item_pic.jpg","sold":"0","quantity":0,"totalSoldQuantity":0,"url":"//detail.m.tmall.com/item.htm?id=543750536702","price":"1474.20"},{"item_id":549012061606,"title":"FOOK CHAK YAN/福泽人足金手镯 黄金手镯实心小巧镯子19号计价","img":"//img.alicdn.com/bao/uploaded/i3/TB1EuPCQFXXXXaaXFXXXXXXXXXX_!!0-item_pic.jpg","sold":"0","quantity":0,"totalSoldQuantity":0,"url":"//detail.m.tmall.com/item.htm?id=549012061606","price":"3619.20"},{"item_id":548219507676,"title":"FOOK CHAK YAN/福泽人足金吊坠 心花怒放黄金吊坠精工款 计价","img":"//img.alicdn.com/bao/uploaded/i1/TB1Q8gbQpXXXXc3XVXXXXXXXXXX_!!0-item_pic.jpg","sold":"0","quantity":0,"totalSoldQuantity":0,"url":"//detail.m.tmall.com/item.htm?id=548219507676","price":"809.60"},{"item_id":549039954165,"title":"FOOK CHAK YAN/福泽人足金手镯 可调节光面实心圆形黄金镯子计价","img":"//img.alicdn.com/bao/uploaded/i2/TB1dnHLQFXXXXa9XFXXXXXXXXXX_!!0-item_pic.jpg","sold":"0","quantity":0,"totalSoldQuantity":0,"url":"//detail.m.tmall.com/item.htm?id=549039954165","price":"11539.20"},{"item_id":548967284441,"title":"FOOK CHAK YAN/福泽人足金手镯 黄金手镯妈妈礼物女镯子 计价","img":"//img.alicdn.com/bao/uploaded/i3/TB1SQzxQFXXXXbUXVXXXXXXXXXX_!!0-item_pic.jpg","sold":"0","quantity":0,"totalSoldQuantity":0,"url":"//detail.m.tmall.com/item.htm?id=548967284441","price":"6924.80"},{"item_id":544205425054,"title":"FOOK CHAK YAN/福泽人18K金钻戒 圆钻心形戒指国检证书 定价","img":"//img.alicdn.com/bao/uploaded/i3/TB1gThdQXXXXXcmXXXXXXXXXXXX_!!0-item_pic.jpg","sold":"0","quantity":0,"totalSoldQuantity":5,"url":"//detail.m.tmall.com/item.htm?id=544205425054","price":"1284.48"},{"item_id":548239126753,"title":"FOOK CHAK YAN/福泽人足金吊坠 快乐音符吊坠送女友送恋人计价","img":"//img.alicdn.com/bao/uploaded/i3/TB1NEUcQpXXXXa4aXXXXXXXXXXX_!!0-item_pic.jpg","sold":"0","quantity":0,"totalSoldQuantity":0,"url":"//detail.m.tmall.com/item.htm?id=548239126753","price":"492.80"},{"item_id":543773321476,"title":"FOOK CHAK YAN/福泽人黄金桃花女戒 足金999戒指三朵桃花定价","img":"//img.alicdn.com/bao/uploaded/i1/TB1PIFaQXXXXXX4XpXXXXXXXXXX_!!0-item_pic.jpg","sold":"0","quantity":0,"totalSoldQuantity":0,"url":"//detail.m.tmall.com/item.htm?id=543773321476","price":"1385.80"},{"item_id":544505124270,"title":"FOOK CHAK YAN/福泽人钻石戒指 18K玫瑰金碎钻皇冠戒指钻戒定价","img":"//img.alicdn.com/bao/uploaded/i1/TB1tjo5PVXXXXaxXFXXXXXXXXXX_!!0-item_pic.jpg","sold":"0","quantity":0,"totalSoldQuantity":0,"url":"//detail.m.tmall.com/item.htm?id=544505124270","price":"1237.44"},{"item_id":544910284415,"title":"FOOK CHAK YAN/福泽人足金套链 黄金简花锁骨链带坠链免工费计价","img":"//img.alicdn.com/bao/uploaded/i2/TB1AbkwPVXXXXbuaFXXXXXXXXXX_!!0-item_pic.jpg","sold":"0","quantity":0,"totalSoldQuantity":0,"url":"//detail.m.tmall.com/item.htm?id=544910284415","price":"1568.00"},{"item_id":543106158110,"title":"FOOK CHAK YAN/福泽人足金戒指 黄金999玫瑰女士戒指 定价","img":"//img.alicdn.com/bao/uploaded/i4/TB1wSA0PVXXXXbcXFXXXXXXXXXX_!!0-item_pic.jpg","sold":"0","quantity":0,"totalSoldQuantity":1,"url":"//detail.m.tmall.com/item.htm?id=543106158110","price":"887.25"},{"item_id":548088157606,"title":"FOOK CHAK YAN/福泽人足金吊坠 黄金蝴蝶小巧吊坠可爱坠子 计价","img":"//img.alicdn.com/bao/uploaded/i3/TB1UITIQpXXXXbFaXXXXXXXXXXX_!!0-item_pic.jpg","sold":"0","quantity":0,"totalSoldQuantity":0,"url":"//detail.m.tmall.com/item.htm?id=548088157606","price":"675.20"},{"item_id":548072537181,"title":"FOOK CHAK YAN/福泽人足金吊坠 黄金心连心坠子分三期免手续费","img":"//img.alicdn.com/bao/uploaded/i3/TB1FSwiQpXXXXaEXXXXXXXXXXXX_!!0-item_pic.jpg","sold":"0","quantity":0,"totalSoldQuantity":0,"url":"//detail.m.tmall.com/item.htm?id=548072537181","price":"838.40"},{"item_id":549068763964,"title":"FOOK CHAK YAN/福泽人足金手镯 实心镯子小巧可爱女生款18号计价","img":"//img.alicdn.com/bao/uploaded/i3/TB10SjyQFXXXXXuXVXXXXXXXXXX_!!0-item_pic.jpg","sold":"0","quantity":0,"totalSoldQuantity":0,"url":"//detail.m.tmall.com/item.htm?id=549068763964","price":"4441.60"},{"item_id":548110842308,"title":"FOOK CHAK YAN/福泽人足金吊坠 爱心翅膀黄金简单坠子 计价","img":"//img.alicdn.com/bao/uploaded/i1/TB1chHEQpXXXXbaaXXXXXXXXXXX_!!0-item_pic.jpg","sold":"0","quantity":0,"totalSoldQuantity":0,"url":"//detail.m.tmall.com/item.htm?id=548110842308","price":"816.00"},{"item_id":544439446798,"title":"FOOK CHAK YAN/福泽人黄金女戒 足金999开口不对称花朵戒指计价","img":"//img.alicdn.com/bao/uploaded/i3/TB1MQIrPVXXXXXrXFXXXXXXXXXX_!!0-item_pic.jpg","sold":"0","quantity":0,"totalSoldQuantity":0,"url":"//detail.m.tmall.com/item.htm?id=544439446798","price":"998.40"},{"item_id":544594475045,"title":"FOOK CHAK YAN/福泽人黄金女戒 足金999戒指开口活口戒免工费计价","img":"//img.alicdn.com/bao/uploaded/i2/TB1hisPPVXXXXb7XVXXXXXXXXXX_!!0-item_pic.jpg","sold":"0","quantity":0,"totalSoldQuantity":0,"url":"//detail.m.tmall.com/item.htm?id=544594475045","price":"2400.00"}],"current_page":"3","page_size":"24","total_results":"98"}