[{"detail":"我强烈建议对于1g金币加大销量，对于3g以上的金币减少销量！！！我们真正买得起的1g金币抢不到，买不起的3g-30g金币一直卖不完，请问这样到底有什么意思呢？想买的买不到，不想买的金币却多得卖不完？","item_id":66,"account":"雷****o","replyTime":"2017-03-16 10:39:49","postTime":"2017-03-16 10:38:32","negative":0.6697854399681091,"positive":0.3302145600318909},{"detail":"2月8日商城回复说3克熊猫金币的目前库存只有200多枚，请问200多枚销售完毕后还会不会再增加货量，再次销售？","item_id":66,"account":"雷****o","replyTime":"2017-02-17 13:18:07","postTime":"2017-02-17 12:03:19","negative":0.4235558807849884,"positive":0.5764440894126892},{"detail":"请问2017年3克什么时间有货？","item_id":66,"account":"z*****0","replyTime":"2017-02-16 15:44:59","postTime":"2017-02-16 15:37:43","negative":0.5,"positive":0.5},{"detail":"请问金币商城上的2016年3g的金币最终封装数量数多少，可以告知一下吗？","item_id":66,"account":"z***i","replyTime":"2017-02-09 15:03:12","postTime":"2017-02-09 14:53:16","negative":0.4197854995727539,"positive":0.5802145004272461},{"detail":"2016年3g的金币计划封装多少枚，目前封装了多少枚？","item_id":66,"account":"z****i","replyTime":"2017-02-08 06:17:43","postTime":"2017-02-08 00:01:26","negative":0.5,"positive":0.5},{"detail":"请问2016年3g的金币还有多少库存未卖出，2017年1g和3g的金币什么时候有货？","item_id":66,"account":"z*****i","replyTime":"2017-02-07 06:44:17","postTime":"2017-02-06 22:20:31","negative":0.5,"positive":0.5},{"detail":"请问：2016年1g的金币还会上架吗？","item_id":66,"account":"z***i","replyTime":"2017-02-07 06:43:22","postTime":"2017-02-06 19:45:37","negative":0.4061112999916077,"positive":0.5938887000083923},{"detail":"您还。现在拍下什么时候发货","item_id":66,"account":"马***龙","replyTime":"2017-01-16 19:55:13","postTime":"2017-01-16 12:38:28","negative":0.5,"positive":0.5},{"detail":"网上商城的购买付款链接在哪？","item_id":66,"account":"t****9","replyTime":"2017-01-12 13:47:36","postTime":"2017-01-12 11:44:31","negative":0.5,"positive":0.5},{"detail":"会员编号是什么","item_id":66,"account":"1****q","replyTime":"2016-12-30 14:25:15","postTime":"2016-12-30 14:21:01","negative":0.5,"positive":0.5},{"detail":"16年3g金币还上架么？","item_id":66,"account":"g***9","replyTime":"2016-12-27 16:52:41","postTime":"2016-12-27 16:51:05","negative":0.5,"positive":0.5},{"detail":"怎么16的3克比17的3克贵？","item_id":66,"account":"1****2","replyTime":"2016-12-24 05:46:47","postTime":"2016-12-23 18:13:29","negative":0.5,"positive":0.5},{"detail":"请问17福币何时销售，账号被锁定了怎么查询？谢谢","item_id":66,"account":"相****早","replyTime":"2016-12-22 14:52:19","postTime":"2016-12-22 14:48:57","negative":0.1208867579698563,"positive":0.8791131973266602},{"detail":"问下，17年福币何时在商城销售，价多少","item_id":66,"account":"f*****7","replyTime":"2016-12-22 14:48:16","postTime":"2016-12-22 12:45:13","negative":0.5,"positive":0.5},{"detail":"收到寄来的货，想打开看下，但那封装的胶盒怎样弄都打不开？请问是什么原因？","item_id":66,"account":"L****8","replyTime":"2016-12-19 13:50:15","postTime":"2016-12-19 11:58:46","negative":0.9061231017112732,"positive":0.0938769057393074},{"detail":"2017年3克的可以一起买吗？","item_id":66,"account":"z***0","replyTime":"2016-12-19 09:31:14","postTime":"2016-12-19 08:54:18","negative":0.5198279619216919,"positive":0.4801720380783081},{"detail":"请问2016年3克封装金币，贵公司一共封装了多少枚？謝谢回复！","item_id":66,"account":"唐*****8","replyTime":"2016-12-14 09:07:33","postTime":"2016-12-14 08:25:00","negative":0.5,"positive":0.5},{"detail":"2016年的熊猫一克金币还会有销售吗？如果有会用什么方式销售呢？","item_id":66,"account":"唐*****8","replyTime":"2016-12-12 06:47:05","postTime":"2016-12-10 16:13:17","negative":0.4061112999916077,"positive":0.5938887000083923},{"detail":"你好，昨天下的3克熊猫金的单，大概什么时候发货？从哪发货的？","item_id":66,"account":"浦*****香","replyTime":"2016-12-07 14:18:35","postTime":"2016-12-06 20:22:12","negative":0.1000000014901161,"positive":0.8999999761581421},{"detail":"17年三元福币什么时候开卖？是抢购还是抽签？商城有多少枚可卖？","item_id":66,"account":"h****j","replyTime":"2016-12-05 08:50:08","postTime":"2016-12-03 23:10:07","negative":0.5,"positive":0.5},{"detail":"封装金币买回怎么保存，还需要另外买保护盒之类的么？","item_id":66,"account":"t***j","replyTime":"2016-12-01 06:54:17","postTime":"2016-11-30 21:13:40"},{"detail":"你好我收到金币了打不开是本来就打不开吗？还有为什么没有证书？请问3g的都没有证书吗？","item_id":66,"account":"h***6","replyTime":"2016-11-22 13:41:27","postTime":"2016-11-22 11:39:18","negative":0.635272204875946,"positive":0.3647278249263763},{"detail":"我买的3克金币，说明书配的是30克的说明书，并不是你说的统一的说明书，原物与说明书不匹配，我买的这个是送朋友的，不匹配怎么送","item_id":66,"account":"尚*****敏","replyTime":"2016-11-22 11:32:01","postTime":"2016-11-22 09:05:00","negative":0.7839047908782959,"positive":0.2160952091217041},{"detail":"我买的是2016年3克金猫，怎么配的金币说明书是2016年30克金币的说明书？说明书:重量30克，直径32，成色99.9，面额500元","item_id":66,"account":"尚****敏","replyTime":"2016-11-22 06:36:22","postTime":"2016-11-21 20:15:42","negative":0.5,"positive":0.5},{"detail":"请问，订单号294633，快递单号是CAE611328677，为什么最后收到的快递单号却不是这个，打电话问顺丰，说你们物流跟踪上的号码肯定不对的，是什么原因造成的，问题在哪，金币的质量还能保证吗？","item_id":66,"account":"秋****8","replyTime":"2016-11-21 07:34:37","postTime":"2016-11-20 20:07:53","negative":0.7205562591552734,"positive":0.2794437408447266},{"detail":"请问一下，封装币的RFID芯片的信息是不能修改的吧？","item_id":66,"account":"i****h","replyTime":"2016-11-21 07:33:11","postTime":"2016-11-20 20:01:54"},{"detail":"支付宝为什么付不了款","item_id":66,"account":"尚***敏","replyTime":"2016-11-16 14:49:05","postTime":"2016-11-16 10:39:54","negative":0.6265122294425964,"positive":0.373487800359726},{"detail":"您好，购买东西已有4天，民航快递还在出库中，怎么这么慢呀？","item_id":66,"account":"1****5","replyTime":"2016-11-16 06:49:15","postTime":"2016-11-15 18:10:41","negative":0.5168989896774292,"positive":0.4831010401248932},{"detail":"没有实名认证不能购买？","item_id":66,"account":"q*****s","replyTime":"2016-11-16 06:47:58","postTime":"2016-11-15 17:38:20","negative":0.6249033808708191,"positive":0.3750965893268585},{"detail":"请问给我发的是什么快递？","item_id":66,"account":"z***f","replyTime":"2016-11-14 14:33:20","postTime":"2016-11-14 14:27:54","negative":0.5,"positive":0.5},{"detail":"买熊猫币到那里签协议.","item_id":66,"account":"刘*****水","replyTime":"2016-11-14 11:38:10","postTime":"2016-11-14 11:34:43","negative":0.5,"positive":0.5},{"detail":"如何注册实名认证会员？","item_id":66,"account":"红****晓","replyTime":"2016-11-14 10:59:34","postTime":"2016-11-14 10:57:50","negative":0.5,"positive":0.5},{"detail":"我前几天抢到的2016年的3克金币，什么时候发货？","item_id":66,"account":"z*****f","replyTime":"2016-11-14 06:45:31","postTime":"2016-11-12 16:26:04","negative":0.5,"positive":0.5},{"detail":"我想问下你们快递不送的地方会不会转发其他快递，我联系你们的快递2天了电话都联系不上~不知道你们怎么联系的~~不放心啊","item_id":66,"account":"1*****6","replyTime":"2016-11-14 06:44:54","postTime":"2016-11-12 15:47:24","negative":0.554003119468689,"positive":0.4459968507289886},{"detail":"明天星期六上线销售吗？","item_id":66,"account":"上****西","replyTime":"2016-11-14 06:37:15","postTime":"2016-11-11 17:09:44","negative":0.5,"positive":0.5},{"detail":"双11商城有优惠活动吗","item_id":66,"account":"南*****空","replyTime":"2016-11-10 13:50:28","postTime":"2016-11-10 11:58:19","negative":0.5,"positive":0.5},{"detail":"17年熊猫小规格金币会单独销售么？如果会，大概会放多少呢？","item_id":66,"account":"f***n","replyTime":"2016-11-10 10:53:56","postTime":"2016-11-10 09:46:58","negative":0.5,"positive":0.5},{"detail":"16，17的金币还会有吗？","item_id":66,"account":"1*****1","replyTime":"2016-11-09 09:27:31","postTime":"2016-11-08 17:49:30","negative":0.4061112999916077,"positive":0.5938887000083923},{"detail":"3G装金币熊猫纪念币什么时候还能有货？","item_id":66,"account":"1***6","replyTime":"2016-11-09 09:21:32","postTime":"2016-11-08 10:02:36","negative":0.09796880185604095,"positive":0.9020311832427979},{"detail":"什么时候发货啊！我是11月4日买的……","item_id":66,"account":"楊*****森","replyTime":"2016-11-08 16:38:32","postTime":"2016-11-07 02:37:47","negative":0.5,"positive":0.5},{"detail":"新货何时上架","item_id":66,"account":"s****j","replyTime":"2016-11-07 18:31:19","postTime":"2016-11-04 21:16:30","negative":0.5,"positive":0.5},{"detail":"27号购买的，怎么现在还是配货中？","item_id":66,"account":"D***u","replyTime":"2016-11-01 06:45:48","postTime":"2016-10-31 17:58:50","negative":0.5,"positive":0.5},{"detail":"2017年的3g熊猫金币有售吗","item_id":66,"account":"叶***4","replyTime":"2016-10-31 06:29:53","postTime":"2016-10-29 07:06:39","negative":0.5,"positive":0.5},{"detail":"请商城搞活动时最好放在非工作日时间段，同时弱弱地问一下，商城开始发售2017年封装金银猫以何种形式开展？","item_id":66,"account":"k*****7","replyTime":"2016-10-27 08:39:32","postTime":"2016-10-27 08:37:19","negative":0.2629770934581757,"positive":0.737022876739502},{"detail":"有发票之类的东西吗？","item_id":66,"account":"初*****虹","replyTime":"2016-10-26 19:01:12","postTime":"2016-10-26 17:14:40","negative":0.1470589935779572,"positive":0.8529409766197205},{"detail":"退款怎么这么慢，都十几天了还没退款","item_id":66,"account":"3****i","replyTime":"2016-10-26 06:36:00","postTime":"2016-10-25 17:18:07","negative":0.7842080593109131,"positive":0.2157919555902481},{"detail":"16年熊猫1克金币什么时间发售啊","item_id":66,"account":"j****y","replyTime":"2016-10-24 08:13:15","postTime":"2016-10-22 21:57:47","negative":0.5,"positive":0.5},{"detail":"2017年银猫封装多少枚","item_id":66,"account":"钱***藏","replyTime":"2016-10-21 11:41:49","postTime":"2016-10-21 09:47:37","negative":0.5,"positive":0.5},{"detail":"2016年150克银猫怎么买","item_id":66,"account":"钱****藏","replyTime":"2016-10-21 11:41:20","postTime":"2016-10-21 09:47:17","negative":0.5,"positive":0.5},{"detail":"2017年30克封装银猫什么时候上架","item_id":66,"account":"钱****藏","replyTime":"2016-10-21 11:40:01","postTime":"2016-10-21 09:46:38","negative":0.5,"positive":0.5},{"detail":"哇哈哈哈","item_id":66,"account":"p****a","replyTime":"2016-10-21 09:16:18","postTime":"2016-10-21 09:09:54","negative":0.02865329198539257,"positive":0.9713467359542847},{"detail":"孙中山金银币什么时候会发行？","item_id":66,"account":"1****g","replyTime":"2016-10-14 15:36:13","postTime":"2016-10-14 15:22:37","negative":0.5,"positive":0.5},{"detail":"封装熊猫金币50克及以上的精制币会上架么？","item_id":66,"account":"f*****c","replyTime":"2016-10-14 15:33:02","postTime":"2016-10-14 10:13:46","negative":0.1548780053853989,"positive":0.8451219797134399},{"detail":"请问如果买了商城的钱币博览会门票，在外地的如何购买挂钩抽奖的鸡年生肖纪念币？一定要到博览会现场购买吗？","item_id":66,"account":"j*****l","replyTime":"2016-10-14 15:37:59","postTime":"2016-10-11 10:07:04","negative":0.1993229389190674,"positive":0.8006770610809326},{"detail":"我想问还有一克金币吗一直非常想要一枚","item_id":66,"account":"3*****3","replyTime":"2016-10-14 15:46:34","postTime":"2016-09-30 01:38:49","negative":0.3574450016021729,"positive":0.6425549983978271},{"detail":"请问我的动态实名认证可以确认了吗？","item_id":66,"account":"l****6","replyTime":"2016-10-17 10:53:41","postTime":"2016-09-26 17:21:41","negative":0.3998710513114929,"positive":0.6001289486885071},{"detail":"3克金猫会上线么？","item_id":66,"account":"G*****n","replyTime":"2016-02-25 14:43:53","postTime":"2016-02-24 19:23:08","negative":0.5,"positive":0.5},{"detail":"你好，请问今后每种商品上线前都会出公告》一般提前多久出？会有具体数量吗？只能抢吗？","item_id":66,"account":"z*****u","replyTime":"2016-02-24 09:14:26","postTime":"2016-02-23 19:31:30","negative":0.4364525079727173,"positive":0.5635475516319275},{"detail":"1克金猫啥时有货。","item_id":66,"account":"清****士","replyTime":"2016-02-23 14:30:45","postTime":"2016-02-21 20:30:09","negative":0.5,"positive":0.5},{"detail":"我的福字币显示一直显示正在发货，山西地区什么时候能收到了，现在还没有显示快递单号，","item_id":66,"account":"w*****i","replyTime":"2016-01-22 15:40:23","postTime":"2016-01-22 15:25:02","negative":0.6694406270980835,"positive":0.3305594027042389},{"detail":"请问一月中旬到底是哪天，我这身份认证还没有成功","item_id":66,"account":"b***1","replyTime":"2016-01-12 14:06:42","postTime":"2016-01-12 11:50:37","negative":0.5135043859481812,"positive":0.4864955842494965},{"detail":"您好·，请问·发货的话多长时间能到","item_id":66,"account":"1***M","replyTime":"2016-01-13 10:56:04","postTime":"2016-01-10 16:01:07","negative":0.1000000014901161,"positive":0.8999999761581421},{"detail":"我今天实名认证提交审核的，大概什么时候通过啊？实名认证后才能购买商品是吗","item_id":66,"account":"m*****0","replyTime":"2016-01-07 09:34:27","postTime":"2016-01-07 09:24:53","negative":0.3891794085502625,"positive":0.6108205914497375},{"detail":"110盎司的封装币目前无库存，还会有货吗，想买!","item_id":66,"account":"d*****a","replyTime":"2016-01-07 09:17:50","postTime":"2016-01-06 21:39:33","negative":0.4061112999916077,"positive":0.5938887000083923},{"detail":"已经分别买了30克，15克，8克的金猫了，就差3克和1克的了。请问这个月能卖上吗？给个大概时间好吗？谢谢","item_id":66,"account":"鱼****8","replyTime":"2016-01-07 09:19:23","postTime":"2016-01-06 20:43:34","negative":0.465512216091156,"positive":0.5344878435134888},{"detail":"2016贺岁银纪念币，市场上都有人购买到手了！为什么我们金币商城还没有开售呢？","item_id":66,"account":"z***4","replyTime":"2016-01-06 15:20:02","postTime":"2016-01-06 09:48:36","negative":0.3837046921253204,"positive":0.6162952780723572},{"detail":"一直被担心金币在运输过程中会出问题：请问，我购买的金币在快递运输过程中会不会被刻调包？怎样防止被调包？在收货时注意什么？","item_id":66,"account":"w*****g","replyTime":"2016-01-05 16:33:21","postTime":"2016-01-05 16:04:12","negative":0.5967653393745422,"positive":0.4032346308231354},{"detail":"我存200元，现在想退出来，如何退出来","item_id":66,"account":"f*****o","replyTime":"2016-01-05 11:46:23","postTime":"2016-01-05 11:42:28","negative":0.6794285774230957,"positive":0.3205713927745819},{"detail":"请问一下，库存里有什么？哪怕一样也行。","item_id":66,"account":"2*****7","replyTime":"2016-01-06 16:10:41","postTime":"2016-01-04 14:42:44","negative":0.2013382017612457,"positive":0.7986618280410767},{"detail":"2015和2016年的福字贺岁银质纪念币还有的卖吗？","item_id":66,"account":"1****0","replyTime":"2016-01-06 16:34:12","postTime":"2016-01-01 09:45:54","negative":0.09796880185604095,"positive":0.9020311832427979},{"detail":"什么时候能有货销售？？一直都没货阿？？","item_id":66,"account":"1*****0","replyTime":"2015-12-30 09:11:56","postTime":"2015-12-29 20:42:02","negative":0.6339712142944336,"positive":0.3660287857055664},{"detail":"请问3克熊猫币和1克的还能卖吗？如果不卖了好去别地买。麻烦给个大概消息。谢谢","item_id":66,"account":"鱼***8","replyTime":"2015-12-27 19:33:02","postTime":"2015-12-27 09:38:28","negative":0.3399288654327393,"positive":0.660071074962616},{"detail":"亲16年3克和1克的金猫还上架吗期待中","item_id":66,"account":"P****扬","replyTime":"2015-12-27 19:45:10","postTime":"2015-12-26 16:34:47","negative":0.3516018092632294,"positive":0.648398220539093},{"detail":"想购买3克和8克的熊猫纪念币，怎样可以买到？购买时间是什么时候","item_id":66,"account":"z*****o","replyTime":"2015-12-27 19:47:07","postTime":"2015-12-26 14:41:37","negative":0.3792082369327545,"positive":0.6207917332649231},{"detail":"3克和1克到底还能上架吗？请给个准确说法行吗，不上架了好去买别的","item_id":66,"account":"鱼****8","replyTime":"2015-12-27 20:02:25","postTime":"2015-12-25 16:35:17","negative":0.0688197985291481,"positive":0.9311801791191101},{"detail":"单位定向包销是啥意思？曹雪芹银币还有吗？","item_id":66,"account":"我***我","replyTime":"2015-12-27 20:26:28","postTime":"2015-12-25 08:57:50","negative":0.7326662540435791,"positive":0.2673337459564209},{"detail":"3g的熊猫币什么时间有货。","item_id":66,"account":"骑***行","replyTime":"2015-12-27 20:29:03","postTime":"2015-12-24 22:50:37","negative":0.5,"positive":0.5},{"detail":"你好，我的发票什么时候发过来","item_id":66,"account":"郭****杰","replyTime":"2015-12-27 20:58:33","postTime":"2015-12-24 16:22:45","negative":0.1000000014901161,"positive":0.8999999761581421},{"detail":"我想买3克这枚，请问怎么预售？","item_id":66,"account":"z***0","replyTime":"2015-12-24 10:14:11","postTime":"2015-12-23 19:25:50","negative":0.5,"positive":0.5},{"detail":"南非中国年金银纪念币还有吗？怎么买？","item_id":66,"account":"l****e","replyTime":"2015-12-23 10:35:28","postTime":"2015-12-23 09:45:43","negative":0.349579393863678,"positive":0.650420606136322},{"detail":"天天上网看很多遍3克和1克的信息。怎么还没有到货啊。能够快些上货吗？","item_id":66,"account":"鱼*****8","replyTime":"2015-12-22 11:26:26","postTime":"2015-12-20 09:43:31","negative":0.412273645401001,"positive":0.587726354598999},{"detail":"过些上货呗，没有买的了。","item_id":66,"account":"鱼***8","replyTime":"2015-12-18 16:36:24","postTime":"2015-12-17 20:58:19","negative":0.5,"positive":0.5},{"detail":"中国金币电子商城正式上线，东西太少了，什么都是没货","item_id":66,"account":"f*****7","replyTime":"2015-12-17 14:24:35","postTime":"2015-12-16 21:33:50","negative":0.6517680883407593,"positive":0.3482319116592407},{"detail":"这个币什么时候有货啊。","item_id":66,"account":"李****周","replyTime":"2015-12-17 14:23:33","postTime":"2015-12-16 19:40:16","negative":0.5,"positive":0.5},{"detail":"http:www.chinagoldcoin.net 请问，上面就是电子商城的网址？销售信息在这个网上发布？","item_id":66,"account":"l***1","replyTime":"2015-12-16 14:37:39","postTime":"2015-12-16 11:55:31","negative":0.4323073798550767,"positive":0.56769262014492},{"detail":"商城物品太少，又都没货，怎样购买啊！！！！","item_id":66,"account":"y****3","replyTime":"2015-12-16 14:23:08","postTime":"2015-12-16 08:14:00","negative":0.6223204731941223,"positive":0.3776794970035553},{"detail":"什么时候上3克金猫。等着买呢。","item_id":66,"account":"鱼***8","replyTime":"2015-12-16 13:59:35","postTime":"2015-12-15 20:03:21","negative":0.5,"positive":0.5},{"detail":"什么时候结束试运行","item_id":66,"account":"路****生","replyTime":"2015-12-15 16:06:50","postTime":"2015-12-15 15:44:37","negative":0.5,"positive":0.5},{"detail":"从什么渠道会得知销售地与时间的信息","item_id":66,"account":"v***n","replyTime":"2015-12-15 13:43:25","postTime":"2015-12-15 10:53:24","negative":0.5,"positive":0.5},{"detail":"央行今天不是发行福字银币吗？怎么没卖的","item_id":66,"account":"杨****枫","replyTime":"2015-12-15 13:33:20","postTime":"2015-12-15 00:28:20","negative":0.5,"positive":0.5},{"detail":"30克、15克、8克的都买了，而且已经收到货了。3克和1克的什么时候有货啊？买套装的一直能预售，说明3克和1克的也能预售啊，开放3克和1克的预售，考虑一下散买套装的这些用户吧。","item_id":66,"account":"t***h","replyTime":"2015-12-14 15:40:56","postTime":"2015-12-14 15:02:32","negative":0.5403035879135132,"positive":0.4596963822841644},{"detail":"您好，熊猫币现在还有吗，如果有什么时候能预售","item_id":66,"account":"t***o","replyTime":"2015-12-14 15:33:08","postTime":"2015-12-14 11:17:16","negative":0.3505949974060059,"positive":0.6494050025939941},{"detail":"2016版熊猫普制封装金币3克，何时有货呀？","item_id":66,"account":"z***8","replyTime":"2015-12-14 15:27:14","postTime":"2015-12-13 18:14:53","negative":0.5,"positive":0.5},{"detail":"2016贺岁银币怎么预约啊？？？","item_id":66,"account":"小*****子","replyTime":"2015-12-14 15:16:50","postTime":"2015-12-12 23:05:16","negative":0.5,"positive":0.5},{"detail":"除了熊猫币还有什么可以买的","item_id":66,"account":"P*****i","replyTime":"2015-12-14 15:16:29","postTime":"2015-12-12 22:52:16","negative":0.4197854995727539,"positive":0.5802145004272461},{"detail":"为什么现在没法下单订购？","item_id":66,"account":"d***n","replyTime":"2015-12-14 14:27:21","postTime":"2015-12-12 04:36:04","negative":0.6865946054458618,"positive":0.3134053945541382},{"detail":"你好，是不是我想购买纪念币必须要身份认证","item_id":66,"account":"死****浪","replyTime":"2015-12-11 15:08:04","postTime":"2015-12-08 20:58:08","negative":0.09898439794778824,"positive":0.90101557970047},{"detail":"纪念币开售前能短信提醒吗","item_id":66,"account":"y*****2","replyTime":"2015-12-11 16:14:52","postTime":"2015-12-07 15:20:07","negative":0.09796880185604095,"positive":0.9020311832427979},{"detail":"现在有发售时间吗？","item_id":66,"account":"d****6","replyTime":"2015-12-11 16:25:04","postTime":"2015-12-07 10:39:03","negative":0.5,"positive":0.5},{"detail":"注册会员都可以买吗","item_id":66,"account":"l***1","replyTime":"2015-12-08 11:48:09","postTime":"2015-12-06 20:07:46","negative":0.2106470018625259,"positive":0.7893530130386353},{"detail":"什么时候一克和三克猫开始销售啊？","item_id":66,"account":"y***6","replyTime":"2015-12-08 09:17:35","postTime":"2015-12-05 21:36:52","negative":0.5,"positive":0.5},{"detail":"你好！我想购买1g3\bg可以现在预定吗？","item_id":66,"account":"1***0","replyTime":"2015-12-08 09:13:27","postTime":"2015-12-05 16:45:12","negative":0.2598927617073059,"positive":0.7401072382926941},{"detail":"2016年贺岁纪念银币能预订吗？","item_id":66,"account":"g****h","replyTime":"2015-12-08 08:58:58","postTime":"2015-12-05 10:35:37","negative":0.09796880185604095,"positive":0.9020311832427979},{"detail":"1g3g的什么时候有货？会通知吗？","item_id":66,"account":"小*****猫","replyTime":"2015-12-04 14:45:37","postTime":"2015-12-04 11:15:58","negative":0.5,"positive":0.5},{"detail":"想问下你们的网上商城有没有app的？","item_id":66,"account":"2*****3","replyTime":"2015-12-04 10:36:36","postTime":"2015-12-03 22:51:01","negative":0.5,"positive":0.5},{"detail":"网页上说无库存，是卖完了？还是现在没有出售？","item_id":66,"account":"积****家","replyTime":"2015-12-02 10:16:37","postTime":"2015-12-01 21:57:13","negative":0.829291582107544,"positive":0.1707084029912949},{"detail":"3g金币何时有供货，请不要回复“该产品暂未开始销售，请随时关注中国金币电子商城。”这种毫无意义的答复。","item_id":66,"account":"S***I","replyTime":"2015-11-27 14:22:38","postTime":"2015-11-27 14:19:01","negative":0.9414414167404175,"positive":0.0585586242377758},{"detail":"请问生肖金银纪念币各大银行怎么没有销售，谢谢！","item_id":66,"account":"1****8","replyTime":"2015-11-24 15:54:24","postTime":"2015-11-24 12:52:08","negative":0.3536702990531921,"positive":0.6463297605514526},{"detail":"你好，请问2016版1克和3克的熊猫金币到底在商城上销售吗？请给个明确答复，免得我隔一小时就得看看，总担心一不留神卖完了，太折磨人。谢谢","item_id":66,"account":"1*****8","replyTime":"2015-11-20 16:01:52","postTime":"2015-11-20 14:41:53","negative":0.5968050956726074,"positive":0.4031948745250702},{"detail":"我是新注册的会员，请问这款还有货么","item_id":66,"account":"梁*****帅","replyTime":"2015-11-19 14:00:47","postTime":"2015-11-18 17:42:56","negative":0.5,"positive":0.5},{"detail":"你好，你们这个3克与1克的什么时间开售啊，谢谢。","item_id":66,"account":"L*****1","replyTime":"2015-11-19 14:13:25","postTime":"2015-11-18 14:17:43","negative":0.2802505195140839,"positive":0.7197494506835938},{"detail":"3g的什么时候卖","item_id":66,"account":"k***n","replyTime":"2015-11-19 14:25:12","postTime":"2015-11-18 12:42:07","negative":0.5,"positive":0.5},{"detail":"2016版熊猫普制封装金币3克，什么时候有货？","item_id":66,"account":"y*****o","replyTime":"2015-11-19 14:51:00","postTime":"2015-11-18 09:51:50","negative":0.5,"positive":0.5},{"detail":"请问什么时候还能购买？","item_id":66,"account":"g*****6","replyTime":"2015-11-19 14:52:43","postTime":"2015-11-17 22:50:37","negative":0.5,"positive":0.5},{"detail":"想咨询一下什么时候有货","item_id":66,"account":"丶*****熙","replyTime":"2015-11-19 14:54:39","postTime":"2015-11-17 21:41:41","negative":0.5,"positive":0.5},{"detail":"什么时候可以购买","item_id":66,"account":"a****a","replyTime":"2015-11-19 15:01:27","postTime":"2015-11-17 20:56:52","negative":0.07086609303951263,"positive":0.9291338920593262},{"detail":"这个啥时有售？","item_id":66,"account":"果****8","replyTime":"2015-11-19 15:03:24","postTime":"2015-11-17 20:17:45","negative":0.5,"positive":0.5},{"detail":"你好，16金猫1克3克什么时候可以开量预售？","item_id":66,"account":"t***o","replyTime":"2015-11-19 11:15:54","postTime":"2015-11-17 19:50:40","negative":0.2598927617073059,"positive":0.7401072382926941},{"detail":"1克和3克的什么时候开始销售？","item_id":66,"account":"w*****u","replyTime":"2015-11-19 11:00:28","postTime":"2015-11-17 14:51:51","negative":0.6198704242706299,"positive":0.3801296055316925},{"detail":"怎么无法购买啊","item_id":66,"account":"陕***北","replyTime":"2015-11-19 15:42:41","postTime":"2015-11-17 12:28:43","negative":0.6795061826705933,"positive":0.3204937875270844},{"detail":"怎么就是这个没有上架？","item_id":66,"account":"问***蓉","replyTime":"2015-11-19 15:39:51","postTime":"2015-11-17 11:16:37","negative":0.5,"positive":0.5}]