[{"detail":"2016吉祥文化金银纪念币“并蒂同心”封装银币17号没有销售，请问什么时候销售","item_id":99,"account":"1***1","replyTime":"2017-03-16 16:08:09","postTime":"2017-03-16 14:37:43","negative":0.063618503510952,"positive":0.9363815188407898},{"detail":"您好，今年还会补发这款吉祥文化么？","item_id":99,"account":"1*****1","replyTime":"2017-03-14 14:08:50","postTime":"2017-03-14 13:18:59","negative":0.1784598380327225,"positive":0.821540117263794},{"detail":"商城在发布咨询时会员名称请尽量用会员昵称（除非未设昵称），以保护个人资料和隐私，以维护会员权益！","item_id":99,"account":"w***h","replyTime":"2017-03-01 06:30:36","postTime":"2017-02-28 16:04:23","negative":0.2401138991117477,"positive":0.7598860859870911},{"detail":"2017年的吉祥文化系列银币抽签大概什么时候开始？会提前发公告或通知吗？请告知。","item_id":99,"account":"飞***岛","replyTime":"2017-02-21 12:33:43","postTime":"2017-02-21 11:09:53","negative":0.02926819957792759,"positive":0.970731794834137},{"detail":"请问下还会有2016吉祥文化套装发售吗？","item_id":99,"account":"袁*****理","replyTime":"2017-01-16 19:54:54","postTime":"2017-01-16 12:45:38","negative":0.2176897525787354,"positive":0.7823102474212646},{"detail":"以后还会有并蒂同心的纪念币吗？上次没买到","item_id":99,"account":"z***6","replyTime":"2016-12-08 10:44:02","postTime":"2016-12-08 10:41:17","negative":0.2520400583744049,"positive":0.7479599714279175},{"detail":"怎么参与抽签？","item_id":99,"account":"w*****5","replyTime":"2016-10-14 15:39:38","postTime":"2016-10-10 18:53:05","negative":0.5,"positive":0.5},{"detail":"怎样查询中签结果","item_id":99,"account":"1*****8","replyTime":"2016-08-10 11:30:59","postTime":"2016-08-04 12:17:43","negative":0.5,"positive":0.5}]